phenoml/__init__.py
phenoml/agent/__init__.py
phenoml/agent/client.py
phenoml/agent/errors/__init__.py
phenoml/agent/errors/bad_request_error.py
phenoml/agent/errors/forbidden_error.py
phenoml/agent/errors/internal_server_error.py
phenoml/agent/errors/not_found_error.py
phenoml/agent/errors/unauthorized_error.py
phenoml/agent/prompts/__init__.py
phenoml/agent/prompts/client.py
phenoml/agent/prompts/raw_client.py
phenoml/agent/prompts/types/__init__.py
phenoml/agent/prompts/types/prompts_delete_response.py
phenoml/agent/prompts/types/prompts_list_response.py
phenoml/agent/raw_client.py
phenoml/agent/types/__init__.py
phenoml/agent/types/agent_chat_response.py
phenoml/agent/types/agent_create_request.py
phenoml/agent/types/agent_create_request_provider.py
phenoml/agent/types/agent_delete_response.py
phenoml/agent/types/agent_get_chat_messages_request_order.py
phenoml/agent/types/agent_get_chat_messages_request_role.py
phenoml/agent/types/agent_get_chat_messages_response.py
phenoml/agent/types/agent_list_response.py
phenoml/agent/types/agent_prompts_response.py
phenoml/agent/types/agent_response.py
phenoml/agent/types/agent_template.py
phenoml/agent/types/agent_template_provider.py
phenoml/agent/types/chat_message_template.py
phenoml/agent/types/chat_message_template_role.py
phenoml/agent/types/chat_session_template.py
phenoml/agent/types/json_patch.py
phenoml/agent/types/json_patch_operation.py
phenoml/agent/types/json_patch_operation_op.py
phenoml/agent/types/prompt_template.py
phenoml/agent/types/success_response.py
phenoml/authtoken/__init__.py
phenoml/authtoken/auth/__init__.py
phenoml/authtoken/auth/client.py
phenoml/authtoken/auth/raw_client.py
phenoml/authtoken/auth/types/__init__.py
phenoml/authtoken/auth/types/auth_generate_token_response.py
phenoml/authtoken/client.py
phenoml/authtoken/errors/__init__.py
phenoml/authtoken/errors/bad_request_error.py
phenoml/authtoken/errors/unauthorized_error.py
phenoml/authtoken/raw_client.py
phenoml-2.0.0.dist-info/LICENSE
phenoml-2.0.0.dist-info/METADATA
phenoml-2.0.0.dist-info/WHEEL
phenoml-2.0.0.dist-info/RECORD
